mygpt/__init__.py
mygpt/_modidx.py
mygpt/core.py
mygpt/data.py
mygpt-0.0.1.dist-info/LICENSE
mygpt-0.0.1.dist-info/METADATA
mygpt-0.0.1.dist-info/WHEEL
mygpt-0.0.1.dist-info/entry_points.txt
mygpt-0.0.1.dist-info/top_level.txt
mygpt-0.0.1.dist-info/RECORD
