Metadata-Version: 2.1
Name: mygpt
Version: 0.0.1
Summary: A locally runnable LLM
Home-page: https://github.com/amaiya/mygpt
Author: Arun S. Maiya
Author-email: arun@maiya.net
License: Apache Software License 2.0
Keywords: nbdev jupyter notebook python
Classifier: Development Status :: 4 - Beta
Classifier: Intended Audience :: Developers
Classifier: Natural Language :: English
Classifier: Programming Language :: Python :: 3.7
Classifier: Programming Language :: Python :: 3.8
Classifier: Programming Language :: Python :: 3.9
Classifier: Programming Language :: Python :: 3.10
Classifier: License :: OSI Approved :: Apache Software License
Requires-Python: >=3.7
License-File: LICENSE
Requires-Dist: pandas
Requires-Dist: transformers
Requires-Dist: datasets
Requires-Dist: rouge-score
Requires-Dist: nltk
Requires-Dist: tensorboard
Requires-Dist: py7zr
Requires-Dist: evaluate
Provides-Extra: dev
